{
    "Ar36": {
        "error": 0.002047996213251097, 
        "fit": "Linear", 
        "value": 0.14339455489375008
    }, 
    "Ar37": {
        "error": 0.010455827590986217, 
        "fit": "linear", 
        "value": 0.050050344294829865
    }, 
    "Ar38": {
        "error": 0.025180456615362726, 
        "fit": "linear", 
        "value": 0.6875893820101888
    }, 
    "Ar39": {
        "error": 0.03594339798063786, 
        "fit": "Linear", 
        "value": 26.852117096582443
    }, 
    "Ar40": {
        "error": 0.4051885724479606, 
        "fit": "Linear", 
        "value": 4788.8728958152315
    }, 
    "Ar41": {
        "error": 0.007206092697059753, 
        "fit": "Average", 
        "value": 0.24138136468083995
    }
}