{
    "Ar36": {
        "error": 0.0015189647683338423, 
        "fit": "Linear", 
        "value": 0.07098426454625852
    }, 
    "Ar37": {
        "error": 0.009848904623545143, 
        "fit": "linear", 
        "value": 0.04687520862484348
    }, 
    "Ar38": {
        "error": 0.02359663565639944, 
        "fit": "linear", 
        "value": 0.27548851257915996
    }, 
    "Ar39": {
        "error": 0.0290336538733332, 
        "fit": "Linear", 
        "value": 4.719100745151765
    }, 
    "Ar40": {
        "error": 0.06346488431468418, 
        "fit": "Linear", 
        "value": 173.72267120550754
    }, 
    "Ar41": {
        "error": 0.007775311593755783, 
        "fit": "Average", 
        "value": 0.1111771528113543
    }
}