{
    "AX": {
        "error": 0.008740383690384565, 
        "fit": "average", 
        "value": 0.06652914744594397
    }, 
    "CDD": {
        "error": 1.7871315684085943e-05, 
        "fit": "average", 
        "value": 0.00012610403812178314
    }, 
    "H1": {
        "error": 0.007787932773275899, 
        "fit": "average", 
        "value": -0.03838002434497199
    }, 
    "H2": {
        "error": 0.007938431226446298, 
        "fit": "average", 
        "value": 0.0962438094493046
    }, 
    "L1": {
        "error": 0.007906994496585976, 
        "fit": "average", 
        "value": 0.13384625012247567
    }, 
    "L2": {
        "error": 0.002997179093268571, 
        "fit": "average", 
        "value": 0.002602466700603105
    }
}