{
    "AX": {
        "error": 0.0077718781230076885, 
        "fit": "average", 
        "value": 0.047104220411948915
    }, 
    "CDD": {
        "error": 3.6205464024473376e-05, 
        "fit": "average", 
        "value": 0.00040533441632333576
    }, 
    "H1": {
        "error": 0.015054890454106684, 
        "fit": "average", 
        "value": -0.05298399669850452
    }, 
    "H2": {
        "error": 0.008840094693782356, 
        "fit": "average", 
        "value": 0.059928000915347196
    }, 
    "L1": {
        "error": 0.007497688745666075, 
        "fit": "average", 
        "value": 0.13163221839109696
    }, 
    "L2": {
        "error": 0.002966727823123565, 
        "fit": "average", 
        "value": 0.0002521254641176116
    }
}