{
    "AX": {
        "error": 0.009278633546112705, 
        "fit": "average", 
        "value": 0.05096335870950312
    }, 
    "CDD": {
        "error": 4.202592461754743e-06, 
        "fit": "average", 
        "value": 6.004954158096919e-06
    }, 
    "H1": {
        "error": 0.006138045838153348, 
        "fit": "average", 
        "value": -0.02104797010450778
    }, 
    "H2": {
        "error": 0.009380398859200379, 
        "fit": "average", 
        "value": 0.06554009929830419
    }, 
    "L1": {
        "error": 0.008627740561009492, 
        "fit": "average", 
        "value": 0.11608095001802826
    }, 
    "L2": {
        "error": 0.0027026943243927052, 
        "fit": "average", 
        "value": 3.1592065530827304e-05
    }
}