{
    "AX": {
        "error": 0.007446439356905056, 
        "fit": "average", 
        "value": 0.04880268845370932
    }, 
    "CDD": {
        "error": 3.442376194490243e-05, 
        "fit": "average", 
        "value": 0.0004413641424745391
    }, 
    "H1": {
        "error": 0.013527278823329832, 
        "fit": "average", 
        "value": -0.06424341883882047
    }, 
    "H2": {
        "error": 0.008642082731299143, 
        "fit": "average", 
        "value": 0.07996122000462465
    }, 
    "L1": {
        "error": 0.007142824259532291, 
        "fit": "average", 
        "value": 0.12352674406153243
    }, 
    "L2": {
        "error": 0.0033341980658020453, 
        "fit": "average", 
        "value": 0.005611863025549339
    }
}