{
    "AX": {
        "error": 0.005022285875777914, 
        "fit": "average", 
        "value": 0.04062819111022801
    }, 
    "CDD": {
        "error": 5.004128476309727e-06, 
        "fit": "average", 
        "value": 2.0016513884184605e-05
    }, 
    "H1": {
        "error": 0.003379207925425882, 
        "fit": "average", 
        "value": -0.03785976944076059
    }, 
    "H2": {
        "error": 0.00448260050206058, 
        "fit": "average", 
        "value": 0.07346294684734864
    }, 
    "L1": {
        "error": 0.004646448672291123, 
        "fit": "average", 
        "value": 0.1333812825273314
    }, 
    "L2": {
        "error": 0.001984503607524507, 
        "fit": "average", 
        "value": 0.007032499044988405
    }
}