{
    "AX": {
        "error": 0.00818625864835527, 
        "fit": "average", 
        "value": 0.049760647560205415
    }, 
    "CDD": {
        "error": 1.4328929986110702e-05, 
        "fit": "average", 
        "value": 8.406935849969538e-05
    }, 
    "H1": {
        "error": 0.005695899871519277, 
        "fit": "average", 
        "value": -0.022589801354693368
    }, 
    "H2": {
        "error": 0.008995861345302569, 
        "fit": "average", 
        "value": 0.06885851854811112
    }, 
    "L1": {
        "error": 0.006433897319268865, 
        "fit": "average", 
        "value": 0.1411760883282618
    }, 
    "L2": {
        "error": 0.0035656593007267656, 
        "fit": "average", 
        "value": -0.0007289504391233482
    }
}